{
  "id" : "ac:wol09",
  "name" : {
    "en" : "Skye",
    "ja" : "リリィ",
    "ko" : "릴리",
    "zh" : "百合",
    "de" : "Sabine",
    "es" : "Alderia",
    "fr" : "Marilou",
    "it" : "Lupilla",
    "ru" : "Скай"
  },
  "species" : "$wol",
  "personality" : "$normal",
  "personalitySubtype" : 0,
  "gender" : "$fem",
  "birthday" : [ 24, 3 ],
  "hobby" : "$music",
  "colors" : [ "$blue", "$white" ],
  "nameTag" : [ "#40D9E0", "#FFFCE9" ],
  "catchphrase" : {
    "en" : "airmail",
    "ja" : "フワワ",
    "ko" : "후와와",
    "zh" : "花花",
    "de" : "ahiii",
    "es" : "auuu",
    "fr" : "mumuseau",
    "it" : "uuuhlalà",
    "nl" : "luchtpost",
    "ru" : "пилот"
  },
  "clothing" : {
    "default" : "#acnh:peasantblouse/white",
    "rain" : [ "#acnh:dottedraincoat/pink", "#acnh:rainhat/beige" ]
  },
  "umbrella" : "#acnh:lacyparasol",
  "photo" : "#acnh:skyesphoto",
  "poster" : "#acnh:skyesposter",
  "house" : {
    "walls" : "#acnh:blueheartpatternwall",
    "floor" : "#acnh:simplewhiteflooring",
    "music" : "#acnh:forestlife",
    "items" : [
      "#acnh:lilyrecordplayer/1/2",
      "#acnh:woodensimplebed/65",
      "#acnh:pianobench/2",
      "#acnh:doublesofa/4",
      "#acnh:uprightpiano/1",
      "#acnh:floralswag/3",
      "#acnh:snowflakerug",
      "#acnh:woodentable/97",
      "#acnh:woodenendtable/1",
      "#acnh:creamandsugar/2",
      "#acnh:oldfashionedalarmclock",
      "#acnh:woodenchest/1",
      "#acnh:humidifier/1",
      "#acnh:anthuriumplant/3"
    ]
  },
  //Assorted NmlNpcParam data
  "xx_unparsed" : {
    "0_a54f92fd" : "9",
    "1_e2efe82d" : "9",
    "2_5ef86f1f" : "4",
    "3_195815cf" : "4",
    "4_bea84522.HashRef" : "Normal",
    "5_Hobby" : "Music",
    "6_NpcLooks" : "Girl_normal",
    "7_NpcReleaseType" : "",
    "8_Social" : "Normal",
    "9_VmPauseType" : "Stop",
    "10_VmRhythmType" : "Shuffle",
    "11_AccentWall" : "0",
    "12_BromideItemID" : "6740",
    "13_FloorType" : "0",
    "14_PosterItemID" : "10489",
    "15_RainHat" : "9575",
    "16_RainWare" : "11922",
    "17_SmartphoneRemakeCommonPattern" : "1",
    "18_SmartphoneRemakePattern" : "7",
    "19_Tops" : "4247",
    "20_Umbrella" : "9946",
    "21_UniqueID" : "382",
    "22_WallType" : "0",
    "23_BirthMDay" : "24",
    "24_BirthMonth" : "3",
    "25_Color1" : "4",
    "26_Color2" : "12",
    "27_HavokResName" : "NpcNmlClothWol",
    "28_HelperBoneResName" : "NpcNmlHelperBoneWol",
    "29_InitLive" : "1",
    "30_InitRemakeId" : "0",
    "31_Label" : "wol09",
    "32_NpcColor" : "91",
    "33_NpcTalkType" : "0",
    "34_ResName" : "NpcNmlWol09",
    "35_SpecialELink" : "0",
    "36_SpecialSLink" : "0",
    "37_21c5bbd6" : "3",
    "38_e52f0037" : "6",
    "39_42f255d5" : "3"
  }
}