{
	"colors": {
		"theme": {
			"primary":   [ 0.15, 0.30, 0.43, 0.75 ], //#BF264D6E
			"secondary": [ 0.16, 0.54, 0.85, 0.88 ], //#E12A89D9
			"dialogue":  [ 1.00, 0.98, 0.89, 1.00 ], //#FFFFFAE3

			//basic colors, EGA order
			"black":    [ 0.00, 0.00, 0.00, 1.00 ],
			"navy":     [ 0.00, 0.00, 0.67, 1.00 ],
			"green":    [ 0.00, 0.67, 0.00, 1.00 ],
			"teal":     [ 0.00, 0.67, 0.67, 1.00 ],
			"darkred":  [ 0.67, 0.00, 0.00, 1.00 ],
			"purple":   [ 0.67, 0.00, 0.67, 1.00 ],
			"brown":    [ 0.67, 0.33, 0.00, 1.00 ],
			"silver":   [ 0.67, 0.67, 0.67, 1.00 ],
			"gray":     [ 0.33, 0.33, 0.33, 1.00 ],
			"blue":     [ 0.33, 0.33, 1.00, 1.00 ],
			"lime":     [ 0.33, 1.00, 0.33, 1.00 ],
			"cyan":     [ 0.33, 1.00, 1.00, 1.00 ],
			"red":      [ 1.00, 0.33, 0.33, 1.00 ],
			"magenta":  [ 1.00, 0.33, 1.00, 1.00 ],
			"yellow":   [ 1.00, 1.00, 0.33, 1.00 ],
			"white":    [ 1.00, 1.00, 1.00, 1.00 ],

			//same but numbered
			"ega0":  [ 0.00, 0.00, 0.00, 1.00 ],
			"ega1":  [ 0.00, 0.00, 0.67, 1.00 ],
			"ega2":  [ 0.00, 0.67, 0.00, 1.00 ],
			"ega3":  [ 0.00, 0.67, 0.67, 1.00 ],
			"ega4":  [ 0.67, 0.00, 0.00, 1.00 ],
			"ega5":  [ 0.67, 0.00, 0.67, 1.00 ],
			"ega6":  [ 0.67, 0.33, 0.00, 1.00 ],
			"ega7":  [ 0.67, 0.67, 0.67, 1.00 ],
			"ega8":  [ 0.33, 0.33, 0.33, 1.00 ],
			"ega9":  [ 0.33, 0.33, 1.00, 1.00 ],
			"ega10": [ 0.33, 1.00, 0.33, 1.00 ],
			"ega11": [ 0.33, 1.00, 1.00, 1.00 ],
			"ega12": [ 1.00, 0.33, 0.33, 1.00 ],
			"ega13": [ 1.00, 0.33, 1.00, 1.00 ],
			"ega14": [ 1.00, 1.00, 0.33, 1.00 ],
			"ega15": [ 1.00, 1.00, 1.00, 1.00 ]
		},
		"text": [
			[ 0.510, 0.450, 0.340, 1.0 ], //#FF837256 Text
			[ 0.961, 0.506, 0.773, 1.0 ], //#FFF581C5 Town
			[ 0.024, 0.714, 0.820, 1.0 ], //#FF06B6D1 Important
			[ 0.000, 0.761, 0.000, 1.0 ], //#FF00C200 Player
			[ 0.941, 0.549, 0.000, 1.0 ], //#FFF08C00 NPC
			[ 0.510, 0.443, 0.341, 0.5 ], //#80827157 Onomatopoeia
			[ 0.847, 0.247, 0.247, 1.0 ], //#FFD83F3F CampGameRed
			[ 0.365, 0.365, 0.400, 1.0 ], //#FF5D5D66 CampGameBlack
			[ 0.840, 0.980, 0.990, 1.0 ]  //#FFD6FAFC System
		]
	},
	//UI test
	"hotbar": {
		"textures": [
			"ui/panels.png"
		],
		"alpha": 0.75,
		"polygons": [
			[
				[ 0.340, 0.003 ],
				[ 0.980, 0.003 ],
				[ 0.650, 0.950 ],
				[ 0.005, 0.950 ]
			]
		],
		"panels": [
			//{ } //backing panel or whatever
			{
				"position": [ -48, 0 ],
				"type": "sprite",
				"texture": 0, //squares
				"frame": 1, //extend left
				"color": "primary"
				//polygon defaults to -1 for unclickable
			},
			{
				"id": "hotbarButton_1",
				"position": [ 52, 0 ],
				"type": "sprite",
				"texture": 0,
				"frame": 0, //regular
				"color": "primary",
				"polygon": 0
			},
			{
				"id": "hotbarButton_2",
				"position": [ 192, 0 ],
				"type": "sprite",
				"texture": 0,
				//leave the frame for testing.
				"color": "primary",
				"polygon": 0
			},
			{
				"id": "hotbarButton_3",
				"position": [ 332, 0 ],
				"type": "sprite",
				"texture": 0,
				"alpha": 0.5,
				"color": "primary"
			},
			{
				"id": "hotbarButton_4",
				"position": [ 472, 0 ],
				"type": "sprite",
				"texture": 0,
				"alpha": 0.5,
				"color": "primary"
			},
			{
				"position": [ 8, 8 ],
				"type": "text",
				"text": "Hello~",
				"alpha": 2
			}
		]
	}
}